AUTHORS.rst
CONTRIBUTING.rst
HISTORY.rst
LICENSE
MANIFEST.in
README.rst
setup.cfg
setup.py
django_blockstack_auth/__init__.py
django_blockstack_auth/apps.py
django_blockstack_auth/backends.py
django_blockstack_auth/exceptions.py
django_blockstack_auth/models.py
django_blockstack_auth/settings.py
django_blockstack_auth/urls.py
django_blockstack_auth/utils.py
django_blockstack_auth/views.py
django_blockstack_auth.egg-info/PKG-INFO
django_blockstack_auth.egg-info/SOURCES.txt
django_blockstack_auth.egg-info/dependency_links.txt
django_blockstack_auth.egg-info/not-zip-safe
django_blockstack_auth.egg-info/requires.txt
django_blockstack_auth.egg-info/top_level.txt
django_blockstack_auth/migrations/0001_initial.py
django_blockstack_auth/migrations/__init__.py
django_blockstack_auth/static/blockstack/img/icon-192x192.png
django_blockstack_auth/static/blockstack/js/blockstack.js
django_blockstack_auth/templates/blockstack/login.html
django_blockstack_auth/templates/blockstack/logout.html