Metadata-Version: 1.1
Name: django-blockstack-auth
Version: 0.1.2
Summary: Blockstack ID authentication backend for Django
Home-page: https://github.com/dotpodcast/django-blockstack-auth
Author: Mark Steadman
Author-email: mark@steadman.io
License: MIT
Keywords: django-blockstack-auth
Platform: UNKNOWN
Classifier: Development Status :: 3 - Alpha
Classifier: Framework :: Django
Classifier: Framework :: Django :: 1.10
Classifier: Intended Audience :: Developers
Classifier: License :: OSI Approved :: BSD License
Classifier: Natural Language :: English
Classifier: Programming Language :: Python :: 2
Classifier: Programming Language :: Python :: 2.7
Classifier: Programming Language :: Python :: 3
Classifier: Programming Language :: Python :: 3.4
Classifier: Programming Language :: Python :: 3.5
